KinGBERT/__init__.py
KinGBERT/model.py
KinGBERT/utils.py
KinGBERT-0.0.2.dist-info/LICENSE
KinGBERT-0.0.2.dist-info/METADATA
KinGBERT-0.0.2.dist-info/WHEEL
KinGBERT-0.0.2.dist-info/top_level.txt
KinGBERT-0.0.2.dist-info/RECORD
