Metadata-Version: 2.1
Name: KinGBERT
Version: 0.0.2
Summary: Keywords extractor with Graph and BERT methods
Home-page: https://github.com/sokolheavy/KinGBERT
Author: OlenaSokol
Author-email: sokolooo1996@gmail.com
License: MIT
Keywords: Keywords extractions Graph BERT
Platform: UNKNOWN
Classifier: Development Status :: 4 - Beta
Classifier: License :: OSI Approved :: MIT License
Classifier: Programming Language :: Python :: 3
Classifier: Programming Language :: Python :: 3.6
Classifier: Programming Language :: Python :: 3.7
Classifier: Programming Language :: Python :: 3.8
Classifier: Programming Language :: Python :: 3.9
Classifier: Operating System :: OS Independent
Requires-Dist: nltk (==3.6.2)
Requires-Dist: scikit-learn (==0.24.2)
Requires-Dist: spacy (==3.0.6)
Requires-Dist: torch (==1.9.0)
Requires-Dist: transformers (==4.8.0)
